{
  "content": "label", 
  "features": [
    {
      "date": 2003, 
      "id": "2003-JUG-to-SRB", 
      "new_areas": [], 
      "new_labels": [
        "SRB+MNE"
      ], 
      "old_areas": [], 
      "old_labels": [
        "YUG_SRB"
      ], 
      "transition_regions": []
    }, 
    {
      "date": 1992, 
      "id": "1992-JUG-splitup", 
      "new_areas": [
        "SVN", 
        "HRV", 
        "SRB+MNE+KOS", 
        "BIH", 
        "ALB", 
        "MKD"
      ], 
      "new_labels": [
        "SVN", 
        "YUG_SRB", 
        "HRV", 
        "BIH", 
        "MKD"
      ], 
      "old_areas": [
        "SFY"
      ], 
      "old_labels": [
        "SFY"
      ], 
      "transition_regions": []
    }, 
    {
      "date": 1990, 
      "id": "1990-ALB-demo", 
      "new_areas": [], 
      "new_labels": [
        "ALB"
      ], 
      "old_areas": [], 
      "old_labels": [
        "VR_ALB"
      ], 
      "transition_regions": []
    }, 
    {
      "date": 1954, 
      "id": "1954-TRST-end", 
      "new_areas": [
        "ITA", 
        "SFY"
      ], 
      "new_labels": [], 
      "old_areas": [
        "TRST", 
        "ITA-TRST", 
        "SFY-TRST"
      ], 
      "old_labels": [
        "TRST"
      ], 
      "transition_regions": []
    }, 
    {
      "date": 1947, 
      "id": "1947-TRST-creation", 
      "new_areas": [
        "SFY-TRST", 
        "ITA-TRST", 
        "TRST"
      ], 
      "new_labels": [
        "TRST"
      ], 
      "old_areas": [
        "SFY-TRST-WestSVN", 
        "ITA-TRST+DODEC"
      ], 
      "old_labels": [], 
      "transition_regions": []
    }, 
    {
      "date": 1945, 
      "id": "1945-SFY-creation", 
      "new_areas": [], 
      "new_labels": [
        "SFY"
      ], 
      "old_areas": [], 
      "old_labels": [
        "YUG"
      ], 
      "transition_regions": []
    }, 
    {
      "date": 1944, 
      "id": "1944-VR_ALB-creation", 
      "new_areas": [
        "ALB"
      ], 
      "new_labels": [
        "VR_ALB"
      ], 
      "old_areas": [], 
      "old_labels": [], 
      "transition_regions": []
    }, 
    {
      "date": 1929, 
      "id": "1929-VAT-creation", 
      "new_areas": [
        "ITA-TRST+DODEC", 
        "VAT"
      ], 
      "new_labels": [
        "VAT"
      ], 
      "old_areas": [
        "ITA-TRST+DODEC+VAT"
      ], 
      "old_labels": [], 
      "transition_regions": []
    }, 
    {
      "date": 1919, 
      "id": "1919-SouthTyrol-to-ITA", 
      "new_areas": [
        "ITA-TRST+DODEC+VAT"
      ], 
      "new_labels": [], 
      "old_areas": [
        "ITA-SouthTyrol+DODEC+VAT"
      ], 
      "old_labels": [], 
      "transition_regions": []
    }, 
    {
      "date": 1918, 
      "id": "1918-JUG-creation", 
      "new_areas": [
        "SFY-TRST-WestSVN"
      ], 
      "new_labels": [
        "YUG"
      ], 
      "old_areas": [], 
      "old_labels": [], 
      "transition_regions": []
    }, 
    {
      "date": 1866, 
      "id": "1866-ITA-creation", 
      "new_areas": [
        "ITA-SouthTyrol+DODEC+VAT"
      ], 
      "new_labels": [
        "ITA"
      ], 
      "old_areas": [], 
      "old_labels": [], 
      "transition_regions": []
    }, 
    {
      "date": 301, 
      "id": "301-SMR-creation", 
      "new_areas": [
        "SMR"
      ], 
      "new_labels": [
        "SMR"
      ], 
      "old_areas": [], 
      "old_labels": [], 
      "transition_regions": []
    }
  ], 
  "type": "FeatureCollection"
}